CHANGELOG.txt
MANIFEST.in
README.md
setup.py
csnews_multilingual/__init__.py
csnews_multilingual/admin.py
csnews_multilingual/apps.py
csnews_multilingual/context_processors.py
csnews_multilingual/feeds.py
csnews_multilingual/forms.py
csnews_multilingual/models.py
csnews_multilingual/tiny_mce_settings.py
csnews_multilingual/urls.py
csnews_multilingual/views.py
csnews_multilingual.egg-info/PKG-INFO
csnews_multilingual.egg-info/SOURCES.txt
csnews_multilingual.egg-info/dependency_links.txt
csnews_multilingual.egg-info/entry_points.txt
csnews_multilingual.egg-info/not-zip-safe
csnews_multilingual.egg-info/requires.txt
csnews_multilingual.egg-info/top_level.txt
csnews_multilingual/locale/es/LC_MESSAGES/django.po
csnews_multilingual/locale/eu/LC_MESSAGES/django.po
csnews_multilingual/locale/fr/LC_MESSAGES/django.po
csnews_multilingual/migrations/0001_initial.py
csnews_multilingual/migrations/0002_auto_20161116_1114.py
csnews_multilingual/migrations/0003_auto_20161117_1041.py
csnews_multilingual/migrations/0004_auto_20161117_1740.py
csnews_multilingual/migrations/0005_auto_20161117_1745.py
csnews_multilingual/migrations/0006_tagtranslation_slug.py
csnews_multilingual/migrations/0007_auto_20161129_0953.py
csnews_multilingual/migrations/0008_auto_20161201_1145.py
csnews_multilingual/migrations/0009_auto_20170216_1719.py
csnews_multilingual/migrations/__init__.py
csnews_multilingual/templates/comments/comment_block.html
csnews_multilingual/templates/news/archive.html
csnews_multilingual/templates/news/article.html
csnews_multilingual/templates/news/article_by_mail.html
csnews_multilingual/templates/news/articles.html
csnews_multilingual/templates/news/social_buttons.html
csnews_multilingual/utils/load_data.py
csnews_multilingual/utils/load_images.py