Metadata-Version: 1.0
Name: csnews-multilingual
Version: 3.21
Summary: Simple news module
Home-page: http://www.codesyntax.com
Author: Urtzi Odriozola
Author-email: uodriozola@codesyntax.com
License: GPL
Platform: UNKNOWN
